awsm_cli/__init__.py
awsm_cli/awsm_cli.py
awsm_cli/test_awsm_cli.py
awsm_cli-0.0.3.dist-info/LICENSE
awsm_cli-0.0.3.dist-info/METADATA
awsm_cli-0.0.3.dist-info/WHEEL
awsm_cli-0.0.3.dist-info/entry_points.txt
awsm_cli-0.0.3.dist-info/top_level.txt
awsm_cli-0.0.3.dist-info/RECORD
