Metadata-Version: 2.1
Name: awsm-cli
Version: 0.0.3
Summary: CLI menu for awesome list https://github.com/sindresorhus/awesome
Home-page: https://github.com/rand-net/awsm-cli
Author: rand-net
License: MIT
Keywords: awesome list,awesome,resources,lists,mammoths
Platform: UNKNOWN
Classifier: License :: OSI Approved :: MIT License
Classifier: Programming Language :: Python :: 3
Classifier: Programming Language :: Python :: 3.7
Requires-Dist: art
Requires-Dist: prompt-toolkit
Requires-Dist: requests
